python_rucaptcha/__init__.py
python_rucaptcha/__version__.py
python_rucaptcha/amazon_waf.py
python_rucaptcha/atb_captcha.py
python_rucaptcha/audio_captcha.py
python_rucaptcha/bounding_box_captcha.py
python_rucaptcha/captcha_fox.py
python_rucaptcha/capy_puzzle.py
python_rucaptcha/control.py
python_rucaptcha/coordinates_captcha.py
python_rucaptcha/cutcaptcha.py
python_rucaptcha/cyber_siara_captcha.py
python_rucaptcha/datadome_captcha.py
python_rucaptcha/draw_around_captcha.py
python_rucaptcha/friendly_captcha.py
python_rucaptcha/fun_captcha.py
python_rucaptcha/gee_test.py
python_rucaptcha/grid_captcha.py
python_rucaptcha/hcaptcha.py
python_rucaptcha/image_captcha.py
python_rucaptcha/key_captcha.py
python_rucaptcha/lemin_captcha.py
python_rucaptcha/mt_captcha.py
python_rucaptcha/prosopo.py
python_rucaptcha/re_captcha.py
python_rucaptcha/rotate_captcha.py
python_rucaptcha/temu_captcha.py
python_rucaptcha/tencent.py
python_rucaptcha/text_captcha.py
python_rucaptcha/turnstile.py
python_rucaptcha/vk_captcha.py
python_rucaptcha/core/__init__.py
python_rucaptcha/core/base.py
python_rucaptcha/core/config.py
python_rucaptcha/core/enums.py
python_rucaptcha/core/result_handler.py
python_rucaptcha/core/serializer.py
python_rucaptcha-6.5.0.dist-info/licenses/LICENSE
python_rucaptcha-6.5.0.dist-info/METADATA
python_rucaptcha-6.5.0.dist-info/WHEEL
python_rucaptcha-6.5.0.dist-info/top_level.txt
python_rucaptcha-6.5.0.dist-info/RECORD
